AgNO3/__init__.py
AgNO3/__version__.py
AgNO3/core.py
AgNO3/ua_info.py
AgNO3-0.0.2.dist-info/LICENSE
AgNO3-0.0.2.dist-info/METADATA
AgNO3-0.0.2.dist-info/WHEEL
AgNO3-0.0.2.dist-info/top_level.txt
AgNO3-0.0.2.dist-info/RECORD
