Metadata-Version: 2.1
Name: AgNO3
Version: 0.0.2
Summary: AgNO3 NB666.
Home-page: https://github.com/MrAgNO3/test
Author: AgNO3
Author-email: 1743928515@qq.com
License: MIT
Platform: UNKNOWN
Classifier: License :: OSI Approved :: MIT License
Classifier: Programming Language :: Python
Classifier: Programming Language :: Python :: 3
Classifier: Programming Language :: Python :: 3.6
Classifier: Programming Language :: Python :: Implementation :: CPython
Classifier: Programming Language :: Python :: Implementation :: PyPy
Requires-Python: >=3.6.0
License-File: LICENSE
Requires-Dist: requests
Requires-Dist: tqdm
